__init__.py
snowshoe/__init__.py
snowshoe/snowshoe.py
snowshoe-0.4.2.dist-info/licenses/LICENSE
snowshoe-0.4.2.dist-info/METADATA
snowshoe-0.4.2.dist-info/WHEEL
snowshoe-0.4.2.dist-info/top_level.txt
snowshoe-0.4.2.dist-info/RECORD
