Metadata-Version: 2.4
Name: snowshoe
Version: 0.4.2
Summary: A wrapper on pika
Author-email: Amin Fazlali <amin@fazlali.net>
Project-URL: Homepage, https://github.com/fazlali/snowshoe
Project-URL: Bug Tracker, https://github.com/fazlali/snowshoe/issues
Classifier: Programming Language :: Python :: 3
Classifier: License :: OSI Approved :: MIT License
Classifier: Operating System :: OS Independent
Requires-Python: >=3.7
License-File: LICENSE
Requires-Dist: pika==1.3.2
Dynamic: license-file
